<?xml version="1.0" encoding="utf-8"?>
<openerp>
    <data noupdate="1">

    <!-- Grupos de Impuestos -->
        <record id="tax_group_taxes" model="account.tax.group" forcecreate="1">
            <field name="name">Tax</field>
            <field name="sequence">1</field>
        </record>

	<!-- Configuracion Impositiva: Tax Template -->
    <!-- Impuesto a las ventas -->
        <record id="vat_21_ventas" model="account.tax">
            <field name="name">IVA Ventas 21%</field>
            <field name="description">IVA Ventas 21%</field>
            <field eval="0.21" name="amount"/>
            <field name="type">percent</field>
            <field name="type_tax_use">sale</field>
            <field name="tax_group">vat</field>
            <field name="tax_group_id" ref="tax_group_taxes"/>
        </record>

        <record id="vat_21_nd_ventas" model="account.tax">
            <field name="name">IVA Ventas 21% No Discriminado</field>
            <field name="description">IVA Ventas 21% (ND)</field>
            <field eval="0.21" name="amount"/>
            <field name="type">percent</field>
            <field name="type_tax_use">sale</field>
            <field name="tax_group">vat</field>
            <field name="tax_group_id" ref="tax_group_taxes"/>
        </record>

        <record id="vat_exento_ventas" model="account.tax">
            <field name="name">IVA Ventas Exento</field>
            <field name="description">IVA Ventas Exento</field>
            <field eval="0.0" name="amount"/>
            <field name="type">percent</field>
            <field name="type_tax_use">sale</field>
            <field name="tax_group">vat</field>
            <field name="tax_group_id" ref="tax_group_taxes"/>
        </record>

        <record id="vat_105_ventas" model="account.tax">
            <field name="name">IVA Ventas 10.5%</field>
            <field name="description">IVA Ventas 10.5%</field>
            <field eval="0.1050" name="amount"/>
            <field name="type">percent</field>
            <field name="type_tax_use">sale</field>
            <field name="tax_group">vat</field>
            <field name="tax_group_id" ref="tax_group_taxes"/>
        </record>

    <!-- Impuesto a las compras -->
        <record id="vat_21_compras" model="account.tax">
            <field name="name">IVA Compras 21%</field>
            <field name="description">IVA Compras 21%</field>
            <field eval="0.21" name="amount"/>
            <field name="type">percent</field>
            <field name="type_tax_use">purchase</field>
            <field name="tax_group">vat</field>
            <field name="tax_group_id" ref="tax_group_taxes"/>
        </record>

        <record id="vat_105_compras" model="account.tax">
            <field name="name">IVA Compras 10.5%</field>
            <field name="description">IVA Compras 10.5%</field>
            <field eval="0.1050" name="amount"/>
            <field name="type">percent</field>
            <field name="type_tax_use">purchase</field>
            <field name="tax_group">vat</field>
            <field name="tax_group_id" ref="tax_group_taxes"/>
        </record>
        
    </data>
</openerp>
